yammpy.cp38-win_amd64.pyd
yammpy-0.9.dev0.dist-info/LICENSE
yammpy-0.9.dev0.dist-info/METADATA
yammpy-0.9.dev0.dist-info/WHEEL
yammpy-0.9.dev0.dist-info/top_level.txt
yammpy-0.9.dev0.dist-info/RECORD
