Metadata-Version: 2.1
Name: yammpy
Version: 0.9.dev0
Summary: Yet Another Math Module
Home-page: https://github.com/AjithRamachandran/yamm
Author: Ajith Ramachandran
Author-email: ajithar204@gmail.com
License: MIT
Keywords: Mathematics
Platform: UNKNOWN
Classifier: Programming Language :: Python :: 3
Classifier: License :: OSI Approved :: MIT License
Classifier: Operating System :: OS Independent
Classifier: Programming Language :: Python :: Implementation :: CPython
Requires-Python: >=3.7
License-File: LICENSE
